<PAMDataset>
  <Metadata domain="Esri">
    <MDI key="PyramidResamplingType">NEAREST</MDI>
  </Metadata>
  <PAMRasterBand band="1">
    <Histograms>
      <HistItem>
        <HistMin>0</HistMin>
        <HistMax>1586.1748046875</HistMax>
        <BucketCount>256</BucketCount>
        <IncludeOutOfRange>1</IncludeOutOfRange>
        <Approximate>0</Approximate>
        <HistCounts>87058|15864|14217|12793|11351|8667|6490|5412|4758|4526|3992|3671|3457|3232|2906|2568|2320|2193|2013|1804|1813|1778|1602|1516|1570|1550|1446|1417|1400|1349|1288|1186|1212|1155|1250|1203|1114|1054|1036|1063|991|1005|973|1009|1003|976|977|984|926|883|835|828|826|828|858|794|810|827|848|808|788|759|775|714|719|776|719|724|718|690|670|631|659|647|625|650|591|578|608|559|562|543|540|541|553|503|569|525|527|503|534|493|492|532|556|546|598|527|488|483|408|422|410|414|371|336|341|365|325|334|328|304|327|329|305|282|283|316|293|294|285|264|249|272|294|253|224|201|255|227|214|247|227|228|240|200|207|211|226|155|190|191|172|169|155|152|163|151|157|155|154|171|147|165|120|145|142|135|118|125|107|105|115|110|103|122|91|104|109|104|86|100|82|104|83|83|75|103|88|79|70|68|77|80|78|68|95|72|85|97|95|89|79|62|68|81|71|92|64|72|80|57|66|44|61|50|48|41|32|37|35|39|31|39|27|26|32|32|17|24|17|24|23|25|12|18|11|10|13|10|10|8|8|16|4|11|12|11|9|3|5|5|5|2|3|3|3|3|2|3|3|1|1|0|1|1</HistCounts>
      </HistItem>
    </Histograms>
    <Metadata>
      <MDI key="RepresentationType">ATHEMATIC</MDI>
      <MDI key="STATISTICS_COVARIANCES">60456.8874564538</MDI>
      <MDI key="STATISTICS_MAXIMUM">1586.1748046875</MDI>
      <MDI key="STATISTICS_MEAN">151.94968491717</MDI>
      <MDI key="STATISTICS_MINIMUM">0</MDI>
      <MDI key="STATISTICS_SKIPFACTORX">1</MDI>
      <MDI key="STATISTICS_SKIPFACTORY">1</MDI>
      <MDI key="STATISTICS_STDDEV">245.87982319917</MDI>
    </Metadata>
  </PAMRasterBand>
</PAMDataset>
